{"cameraMode":{"drawMode":0,"name":"Shaded","section":"Shading Mode"},"sceneLighting":false,"audioPlay":false,"sceneViewState":{"showFog":false,"showMaterialUpdate":false,"showSkybox":false,"showFlares":false,"showImageEffects":false,"showParticleSystems":false},"in2DMode":false,"pivot":{"x":0.0,"y":0.3813908100128174,"z":-0.787045955657959},"rotation":{"x":-0.05572515353560448,"y":0.8954428434371948,"z":-0.11716911196708679,"w":-0.4258500635623932},"size":20.277700424194337,"orthographic":false}